sqlgenx.py
sqlgenx-0.1.11.dist-info/LICENSE
sqlgenx-0.1.11.dist-info/METADATA
sqlgenx-0.1.11.dist-info/WHEEL
sqlgenx-0.1.11.dist-info/top_level.txt
sqlgenx-0.1.11.dist-info/RECORD
